Workbook

Sheet Dossiê de Crédito
C2: DOSSIÊ DE VIABILIDADE E CRÉDITO | H2: ✔ APROVADO (76 PTS)
C4: MARCOS HENRIQUE ANDRADE DE MEDEIROS | 30 ANOS
D8: CAPACIDADE TOTAL DE COMPRA LIBERADA PARA NEGOCIAÇÃO
C14: DADOS DE CRÉDITO IA | H14: O SEU INVESTIMENTO HOJE
C16: CRÉDITO CAIXA: | E16: ='Fluxo Detalhado'!D27 | H16: Entrada Disponível / Acordada
C17: SUBSÍDIO (Governo): | E17: ='Fluxo Detalhado'!D29 | H17: ='Fluxo Detalhado'!C13
C18: SALDO FGTS: | E18: ='Fluxo Detalhado'!C14
C22: 💳 PLANO DE FLUXO DE PAGAMENTO (CONSTRUTORA + BANCO)
C24: ENQUADRAMENTO / ITBI | E24: ENTRADA PARCELADA (CONSTRUTORA) | G24: EVOLUÇÃO DE OBRA (MÉDIA) | I24: PRESTAÇÃO MENSAL (PÓS-CHAVES)
C25: ='Fluxo Detalhado'!D33 | E25: ='Fluxo Detalhado'!D31 | I25: ='Fluxo Detalhado'!D30
C27: ="ITBI " & 'Fluxo Detalhado'!D36 | E27: Período: 36 meses | G27: Conforme a obra avança | I27: Financiamento definitivo
D31: 📈 AUMENTO DE PATRIMÔNIO (PROJEÇÃO NA CHAVE)
C33: VALOR DO IMÓVEL (HOJE) | G33: VALOR NA ENTREGA (MÉDIA +30%)
G34: ='Dossiê de Crédito'!C34 * 1.30
C40: 🛡️ A BLINDAGEM 360° MT PARCEIROS
C42: 🏦 1. APROVAÇÃO BANCÁRIA Todo limite é analisado via API direto antes da emissão do contrato. | E42: ⚖️ 2. ANÁLISE JURÍDICA Nossos advogados validam a idoneidade e cláusulas perigosas. | G42: 🏗️ 3. ACOMPANHAMENTO Não abandonamos você. Nossa equipe acompanha as medições de obra. | I42: 👷 4. LAUDO DE ENGENHARIA Selo MT: O fechamento garante que nossa engenheira fará sua Vistoria Final.
C49: ESTE DOSSIÊ É ESTRITAMENTE CONFIDENCIAL E TEM FINS DE PLANEJAMENTO.

Sheet Fluxo Detalhado
A2: MT PARCEIROS · SIMULADOR INTELIGENTE DE CRÉDITO IMOBILIÁRIO | F2: 📍 mtparceiros@gmail.com | 📞 (11) 96036-4355 | 🌐 mtparceiros-alt.github.io
A5: 👤 IDENTIFICAÇÃO DO CLIENTE
B7: Nome do Cliente: | C7: Digite seu nome aqui... | F7: ← Preencha com o nome completo do cliente
B8: Data da Simulação: | C8: =TODAY() | F8: 🏥 Saúde Financeira: | G8: =IF(D28="","⏳ Aguardando dados...",IF(D28<=0.25,"🟢 EXCELENTE",IF(D28<=0.3,"🟡 BOA","🔴 ATENÇÃO")))
A10: 📥 DADOS DE ENTRADA — Preencha os campos destacados
B11: 1. RENDA E RECURSOS
B12: Renda Bruta Familiar (R$): | C12: 8000 | D12: =IFERROR(REPT("█",INT(MIN(20,C12/1000)),),"") | F12: ← Renda total do núcleo familiar
B13: Entrada em Dinheiro (R$): | C13: 15000 | D13: =IFERROR(REPT("█",INT(MIN(20,C13/2000)),),"") | F13: ← Dinheiro disponível para dar de entrada
B14: Saldo FGTS (R$): | C14: 30000 | D14: =IFERROR(REPT("█",INT(MIN(20,C14/2000)),),"") | F14: ← Consulte o app FGTS ou extrato
B15: Carteira Assinada (3+ anos)? | C15: SIM | F15: ← SIM = multiplica o crédito por fator 142x (vs 132x)
B16: 2. COMPROMETIMENTO MENSAL (Despesas)
B17: Aluguel Atual (R$): | C17: 1200 | D17: =IFERROR(REPT("█",INT(MIN(20,C17/500)),),"")
B18: Alimentação (R$): | C18: 800 | D18: =IFERROR(REPT("█",INT(MIN(20,C18/500)),),"")
B19: Transporte (R$): | C19: 400 | D19: =IFERROR(REPT("█",INT(MIN(20,C19/500)),),"")
B20: Outras Dívidas / Fixos (R$): | C20: 0 | D20: =IFERROR(REPT("█",INT(MIN(20,C20/500)),),"")
B21: Outros (R$): | C21: 0 | D21: =IFERROR(REPT("█",INT(MIN(20,C21/500)),),"")
B22: TOTAL DESPESAS MENSAIS: | C22: =IFERROR(SUM(C17:C21),0) | D22: =IFERROR(REPT("█",INT(MIN(20,C22/500))),"") | F22: =IFERROR(IF(C22/C12>0.3,"⚠️ Despesas superam 30% da renda — risco de reprovação","✅ Despesas dentro do limite de 30% da renda"),"")
A24: 📊 ANÁLISE DO FINANCIAMENTO CAIXA — calculado automaticamente
B25: 3. CÁLCULO DO CRÉDITO (MCMV 2025 — Regras Oficiais CAIXA)
B26: Faixa MCMV: | D26: =IFERROR(IF(C12<=2850,"FAIXA 1 — até R$ 2.850",IF(C12<=4700,"FAIXA 2 — até R$ 4.700","FAIXA 3 — até R$ 8.000")),"") | F26: ← Determinada automaticamente pela renda
B27: Seu Crédito CAIXA (Máximo): | D27: =IFERROR(ROUND(MAX(0,(C12*0.3-C22)*IF(C15="SIM",142,132)),0),0) | F27: (Renda × 30% − Despesas) × Fator de Crédito
B28: Comprometimento de Renda: | D28: =IFERROR(C28/C12,0) | F28: Parcela Projetada (R$): | H28: =IFERROR(MAX(0,(C12*0.3)-C22),0)
B29: Subsídio Federal (MCMV): | D29: =IFERROR(IF(C12<=2850,55000,IF(C12<=4700,35000,0)),0) | F29: =IFERROR(IF(C12<=2850,"Faixa 1: R$ 55.000",IF(C12<=4700,"Faixa 2: R$ 35.000","Não se aplica nesta faixa")),"")
B30: Subsídio Casa Paulista (SP): | D30: =IFERROR(IF(C12<=4863,16000,0),0) | F30: =IFERROR(IF(C12<=4863,"✅ R$ 16.000 — elegível","❌ Não elegível nesta faixa de renda"),"")
B32: 💰 PODER DE COMPRA TOTAL: | F32: =IFERROR(C27+C29+C30+C14+C13,0) | I32: Crédito + Subsídios + FGTS + Entrada
A34: 📋 LAUDO EXECUTIVO — gerado automaticamente pelo algoritmo IA
B35: Status da Análise: | D35: =IFERROR(IF(C28/C12<=0.3,"✅ APROVAÇÃO PROVÁVEL","⚠️ RISCO — Comprometimento acima de 30%"),"")
B36: =IFERROR("Simulação preparada para: "&D7,"Simulação preparada para: ---")
B37: RENDA FAMILIAR | D37: CRÉDITO CAIXA MÁX. | F37: PODER DE COMPRA | H37: PARCELA PROJETADA
B38: =IFERROR(C12,0) | D38: =IFERROR(C27,0) | F38: =IFERROR(C32,0) | H38: =IFERROR(H28,0)
B39: SALDO FGTS | D39: COMPROMETIMENTO | F39: SUBSÍDIO TOTAL | H39: MARGEM DE SEGURANÇA
B40: =IFERROR(C14,0) | D40: =IFERROR(C28/C12,0) | F40: =IFERROR(C29+C30,0) | H40: =IFERROR(1-(C28/C12),0)
B42: 4. SCORE DE JORNADA
B43: Pontuação de Aprovação: | D43: =IFERROR(MIN(100,MIN(40,MAX(0,40-((C28/C12-0.25)*200)))+MIN(30,C14/50000*30)+IF(C15="SIM",15,0)+MIN(15,(C13+C14)/5000)),0) | F43: =IFERROR(REPT("★",INT(H42/20))&REPT("☆",5-INT(H42/20)),"☆☆☆☆☆")
B44: =IFERROR("📍 Etapa atual: Simulação → Escolha do Imóvel → Documentação → Contrato → Assinatura","---")
A46: 🏠 ESCOLHA DO IMÓVEL
B47: 5. SELECIONE O IMÓVEL DESEJADO
B48: Imóvel Selecionado: | D48: Selecione um Imóvel... | H48: ← Clique e selecione da lista
B49: Valor Estimado (R$): | D49: =IFERROR(VLOOKUP(D48,SysData,2,FALSE()),0) | F49: =IFERROR(IF(VLOOKUP(D48,SysData,2,FALSE())<=C32,"✅ Dentro do seu poder de compra","⚠️ Acima do seu poder de compra"),"")
B50: Bairro / Localização: | D50: =IFERROR(VLOOKUP(D48,SysData,5,FALSE()),"---")
B51: Status da Obra: | D51: =IFERROR(VLOOKUP(D48,SysData,10,FALSE()),"---") | F51: Prazo de Obra (meses): | H51: =IFERROR(VLOOKUP(D48,SysData,11,FALSE()),"---")
B52: Previsão de Entrega das Chaves: | D52: =IFERROR(TEXT(EDATE(TODAY(),VLOOKUP(D48,SysData,11,FALSE())),"MM/YYYY"),"---") | F52: Ver Imóvel no Site: | H52: =HYPERLINK("https://mtparceiros-alt.github.io/site-mt","🔗 Abrir Imóvel no Site")
A54: 🎯 PLANEJAMENTO DA CONQUISTA — IA Meta
B55: 6. MINHA ESTRATÉGIA FINANCEIRA
B56: Diferença para Entrada (Gap): | D56: =IFERROR(MAX(0,C49-C32),0)
B57: Minha Reserva Mensal (Aporte): | D57: 500 | F57: ← Quanto você consegue guardar por mês?
B58: Aporte Sugerido pela IA: | D58: =IFERROR(IF(C56<=0,0,IF(VLOOKUP(D48,SysData,10,FALSE())="Obra",C56/MAX(1,VLOOKUP(D48,SysData,11,FALSE())),C56/12)),0)
B59: Evolução de Obra (Banco/mês): | D59: =IFERROR(IF(VLOOKUP(D48,SysData,10,FALSE())="Obra",C27*0.0002,0),0)
B60: Prazo Estimado para Meta: | D60: =IFERROR(IF(C56<=0,"✅ Meta já atingida!",INT(C56/MAX(1,C57))&" meses"),"---")
B61: =IFERROR(IF(C12*0.3<=C22,"⚠️ ALERTA: Suas despesas superam sua margem de crédito. Reduza seus custos ou aumente a renda para a CAIXA aprovar.",""),"")
A63: 📅 TRACKER DE APORTES — marque 'Sim' ao realizar cada aporte
B64: 💰 TOTAL APORTADO: | E64: =IFERROR(SUMIF(B68:B103,"Sim",D68:D103)+SUMIF(B68:B103,"Sim",E68:E103),0) | G64: ⏳ SALDO RESTANTE: | H64: =IFERROR(C49-(SUMIF(B68:B103,"Sim",D68:D103)+SUMIF(B68:B103,"Sim",E68:E103)),C49)
B65: =IFERROR("📊 Progresso: "&TEXT(MIN(100,E64/MAX(1,C49)),"0%")&" conquistado | "&REPT("█",INT(MIN(20,E64/MAX(1,C49)*20)))&REPT("░",20-INT(MIN(20,E64/MAX(1,C49)*20)))&" | Faltam: R$ "&TEXT(MAX(0,C49-E64),"#,##0"),"---")
B66: 💡 COMO USAR: Marque 'Sim' na coluna PAGO quando realizar um aporte. O saldo considera apenas valores confirmados.
B67: ✅ Pago? | C67: Mês / Ano | D67: Aporte Mensal (R$) | E67: Extra (13°/Bônus) | F67: Saldo Acumulado (R$) | G67: Meta (R$) | H67: Status | I67: % Obj.
B68: Não | C68: =IFERROR(TEXT(EDATE(TODAY(),0),"MMM/YYYY"),"---") | D68: =IFERROR($C$58,0) | E68: =IFERROR(IF(MONTH(EDATE(TODAY(),0))=12,$C$12*0.5,0),0) | F68: =IFERROR($C$14+IF(B68="Sim",D68+E68,0),0) | G68: =IFERROR($C$49,$C$32) | H68: =IFERROR(IF(F68>=G68,"✅ ATINGIDA","⏳ EM CURSO"),"---") | I68: =IFERROR(TEXT(MIN(100%,F68/MAX(1,G68)),"0%"),"-")
B69: Não | C69: =IFERROR(TEXT(EDATE(TODAY(),1),"MMM/YYYY"),"---") | D69: =IFERROR($C$58,0) | E69: =IFERROR(IF(MONTH(EDATE(TODAY(),1))=12,$C$12*0.5,0),0) | F69: =IFERROR(F68+IF(B69="Sim",D69+E69,0),0) | G69: =IFERROR($C$49,$C$32) | H69: =IFERROR(IF(F69>=G69,"✅ ATINGIDA","⏳ EM CURSO"),"---") | I69: =IFERROR(TEXT(MIN(100%,F69/MAX(1,G69)),"0%"),"-")
B70: Não | C70: =IFERROR(TEXT(EDATE(TODAY(),2),"MMM/YYYY"),"---") | D70: =IFERROR($C$58,0) | E70: =IFERROR(IF(MONTH(EDATE(TODAY(),2))=12,$C$12*0.5,0),0) | F70: =IFERROR(F69+IF(B70="Sim",D70+E70,0),0) | G70: =IFERROR($C$49,$C$32) | H70: =IFERROR(IF(F70>=G70,"✅ ATINGIDA","⏳ EM CURSO"),"---") | I70: =IFERROR(TEXT(MIN(100%,F70/MAX(1,G70)),"0%"),"-")
B71: Não | C71: =IFERROR(TEXT(EDATE(TODAY(),3),"MMM/YYYY"),"---") | D71: =IFERROR($C$58,0) | E71: =IFERROR(IF(MONTH(EDATE(TODAY(),3))=12,$C$12*0.5,0),0) | F71: =IFERROR(F70+IF(B71="Sim",D71+E71,0),0) | G71: =IFERROR($C$49,$C$32) | H71: =IFERROR(IF(F71>=G71,"✅ ATINGIDA","⏳ EM CURSO"),"---") | I71: =IFERROR(TEXT(MIN(100%,F71/MAX(1,G71)),"0%"),"-")
B72: Não | C72: =IFERROR(TEXT(EDATE(TODAY(),4),"MMM/YYYY"),"---") | D72: =IFERROR($C$58,0) | E72: =IFERROR(IF(MONTH(EDATE(TODAY(),4))=12,$C$12*0.5,0),0) | F72: =IFERROR(F71+IF(B72="Sim",D72+E72,0),0) | G72: =IFERROR($C$49,$C$32) | H72: =IFERROR(IF(F72>=G72,"✅ ATINGIDA","⏳ EM CURSO"),"---") | I72: =IFERROR(TEXT(MIN(100%,F72/MAX(1,G72)),"0%"),"-")
B73: Não | C73: =IFERROR(TEXT(EDATE(TODAY(),5),"MMM/YYYY"),"---") | D73: =IFERROR($C$58,0) | E73: =IFERROR(IF(MONTH(EDATE(TODAY(),5))=12,$C$12*0.5,0),0) | F73: =IFERROR(F72+IF(B73="Sim",D73+E73,0),0) | G73: =IFERROR($C$49,$C$32) | H73: =IFERROR(IF(F73>=G73,"✅ ATINGIDA","⏳ EM CURSO"),"---") | I73: =IFERROR(TEXT(MIN(100%,F73/MAX(1,G73)),"0%"),"-")
B74: Não | C74: =IFERROR(TEXT(EDATE(TODAY(),6),"MMM/YYYY"),"---") | D74: =IFERROR($C$58,0) | E74: =IFERROR(IF(MONTH(EDATE(TODAY(),6))=12,$C$12*0.5,0),0) | F74: =IFERROR(F73+IF(B74="Sim",D74+E74,0),0) | G74: =IFERROR($C$49,$C$32) | H74: =IFERROR(IF(F74>=G74,"✅ ATINGIDA","⏳ EM CURSO"),"---") | I74: =IFERROR(TEXT(MIN(100%,F74/MAX(1,G74)),"0%"),"-")
B75: Não | C75: =IFERROR(TEXT(EDATE(TODAY(),7),"MMM/YYYY"),"---") | D75: =IFERROR($C$58,0) | E75: =IFERROR(IF(MONTH(EDATE(TODAY(),7))=12,$C$12*0.5,0),0) | F75: =IFERROR(F74+IF(B75="Sim",D75+E75,0),0) | G75: =IFERROR($C$49,$C$32) | H75: =IFERROR(IF(F75>=G75,"✅ ATINGIDA","⏳ EM CURSO"),"---") | I75: =IFERROR(TEXT(MIN(100%,F75/MAX(1,G75)),"0%"),"-")
B76: Não | C76: =IFERROR(TEXT(EDATE(TODAY(),8),"MMM/YYYY"),"---") | D76: =IFERROR($C$58,0) | E76: =IFERROR(IF(MONTH(EDATE(TODAY(),8))=12,$C$12*0.5,0),0) | F76: =IFERROR(F75+IF(B76="Sim",D76+E76,0),0) | G76: =IFERROR($C$49,$C$32) | H76: =IFERROR(IF(F76>=G76,"✅ ATINGIDA","⏳ EM CURSO"),"---") | I76: =IFERROR(TEXT(MIN(100%,F76/MAX(1,G76)),"0%"),"-")
B77: Não | C77: =IFERROR(TEXT(EDATE(TODAY(),9),"MMM/YYYY"),"---") | D77: =IFERROR($C$58,0) | E77: =IFERROR(IF(MONTH(EDATE(TODAY(),9))=12,$C$12*0.5,0),0) | F77: =IFERROR(F76+IF(B77="Sim",D77+E77,0),0) | G77: =IFERROR($C$49,$C$32) | H77: =IFERROR(IF(F77>=G77,"✅ ATINGIDA","⏳ EM CURSO"),"---") | I77: =IFERROR(TEXT(MIN(100%,F77/MAX(1,G77)),"0%"),"-")
B78: Não | C78: =IFERROR(TEXT(EDATE(TODAY(),10),"MMM/YYYY"),"---") | D78: =IFERROR($C$58,0) | E78: =IFERROR(IF(MONTH(EDATE(TODAY(),10))=12,$C$12*0.5,0),0) | F78: =IFERROR(F77+IF(B78="Sim",D78+E78,0),0) | G78: =IFERROR($C$49,$C$32) | H78: =IFERROR(IF(F78>=G78,"✅ ATINGIDA","⏳ EM CURSO"),"---") | I78: =IFERROR(TEXT(MIN(100%,F78/MAX(1,G78)),"0%"),"-")
B79: Não | C79: =IFERROR(TEXT(EDATE(TODAY(),11),"MMM/YYYY"),"---") | D79: =IFERROR($C$58,0) | E79: =IFERROR(IF(MONTH(EDATE(TODAY(),11))=12,$C$12*0.5,0),0) | F79: =IFERROR(F78+IF(B79="Sim",D79+E79,0),0) | G79: =IFERROR($C$49,$C$32) | H79: =IFERROR(IF(F79>=G79,"✅ ATINGIDA","⏳ EM CURSO"),"---") | I79: =IFERROR(TEXT(MIN(100%,F79/MAX(1,G79)),"0%"),"-")
B80: Não | C80: =IFERROR(TEXT(EDATE(TODAY(),12),"MMM/YYYY"),"---") | D80: =IFERROR($C$58,0) | E80: =IFERROR(IF(MONTH(EDATE(TODAY(),12))=12,$C$12*0.5,0),0) | F80: =IFERROR(F79+IF(B80="Sim",D80+E80,0),0) | G80: =IFERROR($C$49,$C$32) | H80: =IFERROR(IF(F80>=G80,"✅ ATINGIDA","⏳ EM CURSO"),"---") | I80: =IFERROR(TEXT(MIN(100%,F80/MAX(1,G80)),"0%"),"-")
B81: Não | C81: =IFERROR(TEXT(EDATE(TODAY(),13),"MMM/YYYY"),"---") | D81: =IFERROR($C$58,0) | E81: =IFERROR(IF(MONTH(EDATE(TODAY(),13))=12,$C$12*0.5,0),0) | F81: =IFERROR(F80+IF(B81="Sim",D81+E81,0),0) | G81: =IFERROR($C$49,$C$32) | H81: =IFERROR(IF(F81>=G81,"✅ ATINGIDA","⏳ EM CURSO"),"---") | I81: =IFERROR(TEXT(MIN(100%,F81/MAX(1,G81)),"0%"),"-")
B82: Não | C82: =IFERROR(TEXT(EDATE(TODAY(),14),"MMM/YYYY"),"---") | D82: =IFERROR($C$58,0) | E82: =IFERROR(IF(MONTH(EDATE(TODAY(),14))=12,$C$12*0.5,0),0) | F82: =IFERROR(F81+IF(B82="Sim",D82+E82,0),0) | G82: =IFERROR($C$49,$C$32) | H82: =IFERROR(IF(F82>=G82,"✅ ATINGIDA","⏳ EM CURSO"),"---") | I82: =IFERROR(TEXT(MIN(100%,F82/MAX(1,G82)),"0%"),"-")
B83: Não | C83: =IFERROR(TEXT(EDATE(TODAY(),15),"MMM/YYYY"),"---") | D83: =IFERROR($C$58,0) | E83: =IFERROR(IF(MONTH(EDATE(TODAY(),15))=12,$C$12*0.5,0),0) | F83: =IFERROR(F82+IF(B83="Sim",D83+E83,0),0) | G83: =IFERROR($C$49,$C$32) | H83: =IFERROR(IF(F83>=G83,"✅ ATINGIDA","⏳ EM CURSO"),"---") | I83: =IFERROR(TEXT(MIN(100%,F83/MAX(1,G83)),"0%"),"-")
B84: Não | C84: =IFERROR(TEXT(EDATE(TODAY(),16),"MMM/YYYY"),"---") | D84: =IFERROR($C$58,0) | E84: =IFERROR(IF(MONTH(EDATE(TODAY(),16))=12,$C$12*0.5,0),0) | F84: =IFERROR(F83+IF(B84="Sim",D84+E84,0),0) | G84: =IFERROR($C$49,$C$32) | H84: =IFERROR(IF(F84>=G84,"✅ ATINGIDA","⏳ EM CURSO"),"---") | I84: =IFERROR(TEXT(MIN(100%,F84/MAX(1,G84)),"0%"),"-")
B85: Não | C85: =IFERROR(TEXT(EDATE(TODAY(),17),"MMM/YYYY"),"---") | D85: =IFERROR($C$58,0) | E85: =IFERROR(IF(MONTH(EDATE(TODAY(),17))=12,$C$12*0.5,0),0) | F85: =IFERROR(F84+IF(B85="Sim",D85+E85,0),0) | G85: =IFERROR($C$49,$C$32) | H85: =IFERROR(IF(F85>=G85,"✅ ATINGIDA","⏳ EM CURSO"),"---") | I85: =IFERROR(TEXT(MIN(100%,F85/MAX(1,G85)),"0%"),"-")
B86: Não | C86: =IFERROR(TEXT(EDATE(TODAY(),18),"MMM/YYYY"),"---") | D86: =IFERROR($C$58,0) | E86: =IFERROR(IF(MONTH(EDATE(TODAY(),18))=12,$C$12*0.5,0),0) | F86: =IFERROR(F85+IF(B86="Sim",D86+E86,0),0) | G86: =IFERROR($C$49,$C$32) | H86: =IFERROR(IF(F86>=G86,"✅ ATINGIDA","⏳ EM CURSO"),"---") | I86: =IFERROR(TEXT(MIN(100%,F86/MAX(1,G86)),"0%"),"-")
B87: Não | C87: =IFERROR(TEXT(EDATE(TODAY(),19),"MMM/YYYY"),"---") | D87: =IFERROR($C$58,0) | E87: =IFERROR(IF(MONTH(EDATE(TODAY(),19))=12,$C$12*0.5,0),0) | F87: =IFERROR(F86+IF(B87="Sim",D87+E87,0),0) | G87: =IFERROR($C$49,$C$32) | H87: =IFERROR(IF(F87>=G87,"✅ ATINGIDA","⏳ EM CURSO"),"---") | I87: =IFERROR(TEXT(MIN(100%,F87/MAX(1,G87)),"0%"),"-")
B88: Não | C88: =IFERROR(TEXT(EDATE(TODAY(),20),"MMM/YYYY"),"---") | D88: =IFERROR($C$58,0) | E88: =IFERROR(IF(MONTH(EDATE(TODAY(),20))=12,$C$12*0.5,0),0) | F88: =IFERROR(F87+IF(B88="Sim",D88+E88,0),0) | G88: =IFERROR($C$49,$C$32) | H88: =IFERROR(IF(F88>=G88,"✅ ATINGIDA","⏳ EM CURSO"),"---") | I88: =IFERROR(TEXT(MIN(100%,F88/MAX(1,G88)),"0%"),"-")
B89: Não | C89: =IFERROR(TEXT(EDATE(TODAY(),21),"MMM/YYYY"),"---") | D89: =IFERROR($C$58,0) | E89: =IFERROR(IF(MONTH(EDATE(TODAY(),21))=12,$C$12*0.5,0),0) | F89: =IFERROR(F88+IF(B89="Sim",D89+E89,0),0) | G89: =IFERROR($C$49,$C$32) | H89: =IFERROR(IF(F89>=G89,"✅ ATINGIDA","⏳ EM CURSO"),"---") | I89: =IFERROR(TEXT(MIN(100%,F89/MAX(1,G89)),"0%"),"-")
B90: Não | C90: =IFERROR(TEXT(EDATE(TODAY(),22),"MMM/YYYY"),"---") | D90: =IFERROR($C$58,0) | E90: =IFERROR(IF(MONTH(EDATE(TODAY(),22))=12,$C$12*0.5,0),0) | F90: =IFERROR(F89+IF(B90="Sim",D90+E90,0),0) | G90: =IFERROR($C$49,$C$32) | H90: =IFERROR(IF(F90>=G90,"✅ ATINGIDA","⏳ EM CURSO"),"---") | I90: =IFERROR(TEXT(MIN(100%,F90/MAX(1,G90)),"0%"),"-")
B91: Não | C91: =IFERROR(TEXT(EDATE(TODAY(),23),"MMM/YYYY"),"---") | D91: =IFERROR($C$58,0) | E91: =IFERROR(IF(MONTH(EDATE(TODAY(),23))=12,$C$12*0.5,0),0) | F91: =IFERROR(F90+IF(B91="Sim",D91+E91,0),0) | G91: =IFERROR($C$49,$C$32) | H91: =IFERROR(IF(F91>=G91,"✅ ATINGIDA","⏳ EM CURSO"),"---") | I91: =IFERROR(TEXT(MIN(100%,F91/MAX(1,G91)),"0%"),"-")
B92: Não | C92: =IFERROR(TEXT(EDATE(TODAY(),24),"MMM/YYYY"),"---") | D92: =IFERROR($C$58,0) | E92: =IFERROR(IF(MONTH(EDATE(TODAY(),24))=12,$C$12*0.5,0),0) | F92: =IFERROR(F91+IF(B92="Sim",D92+E92,0),0) | G92: =IFERROR($C$49,$C$32) | H92: =IFERROR(IF(F92>=G92,"✅ ATINGIDA","⏳ EM CURSO"),"---") | I92: =IFERROR(TEXT(MIN(100%,F92/MAX(1,G92)),"0%"),"-")
B93: Não | C93: =IFERROR(TEXT(EDATE(TODAY(),25),"MMM/YYYY"),"---") | D93: =IFERROR($C$58,0) | E93: =IFERROR(IF(MONTH(EDATE(TODAY(),25))=12,$C$12*0.5,0),0) | F93: =IFERROR(F92+IF(B93="Sim",D93+E93,0),0) | G93: =IFERROR($C$49,$C$32) | H93: =IFERROR(IF(F93>=G93,"✅ ATINGIDA","⏳ EM CURSO"),"---") | I93: =IFERROR(TEXT(MIN(100%,F93/MAX(1,G93)),"0%"),"-")
B94: Não | C94: =IFERROR(TEXT(EDATE(TODAY(),26),"MMM/YYYY"),"---") | D94: =IFERROR($C$58,0) | E94: =IFERROR(IF(MONTH(EDATE(TODAY(),26))=12,$C$12*0.5,0),0) | F94: =IFERROR(F93+IF(B94="Sim",D94+E94,0),0) | G94: =IFERROR($C$49,$C$32) | H94: =IFERROR(IF(F94>=G94,"✅ ATINGIDA","⏳ EM CURSO"),"---") | I94: =IFERROR(TEXT(MIN(100%,F94/MAX(1,G94)),"0%"),"-")
B95: Não | C95: =IFERROR(TEXT(EDATE(TODAY(),27),"MMM/YYYY"),"---") | D95: =IFERROR($C$58,0) | E95: =IFERROR(IF(MONTH(EDATE(TODAY(),27))=12,$C$12*0.5,0),0) | F95: =IFERROR(F94+IF(B95="Sim",D95+E95,0),0) | G95: =IFERROR($C$49,$C$32) | H95: =IFERROR(IF(F95>=G95,"✅ ATINGIDA","⏳ EM CURSO"),"---") | I95: =IFERROR(TEXT(MIN(100%,F95/MAX(1,G95)),"0%"),"-")
B96: Não | C96: =IFERROR(TEXT(EDATE(TODAY(),28),"MMM/YYYY"),"---") | D96: =IFERROR($C$58,0) | E96: =IFERROR(IF(MONTH(EDATE(TODAY(),28))=12,$C$12*0.5,0),0) | F96: =IFERROR(F95+IF(B96="Sim",D96+E96,0),0) | G96: =IFERROR($C$49,$C$32) | H96: =IFERROR(IF(F96>=G96,"✅ ATINGIDA","⏳ EM CURSO"),"---") | I96: =IFERROR(TEXT(MIN(100%,F96/MAX(1,G96)),"0%"),"-")
B97: Não | C97: =IFERROR(TEXT(EDATE(TODAY(),29),"MMM/YYYY"),"---") | D97: =IFERROR($C$58,0) | E97: =IFERROR(IF(MONTH(EDATE(TODAY(),29))=12,$C$12*0.5,0),0) | F97: =IFERROR(F96+IF(B97="Sim",D97+E97,0),0) | G97: =IFERROR($C$49,$C$32) | H97: =IFERROR(IF(F97>=G97,"✅ ATINGIDA","⏳ EM CURSO"),"---") | I97: =IFERROR(TEXT(MIN(100%,F97/MAX(1,G97)),"0%"),"-")
B98: Não | C98: =IFERROR(TEXT(EDATE(TODAY(),30),"MMM/YYYY"),"---") | D98: =IFERROR($C$58,0) | E98: =IFERROR(IF(MONTH(EDATE(TODAY(),30))=12,$C$12*0.5,0),0) | F98: =IFERROR(F97+IF(B98="Sim",D98+E98,0),0) | G98: =IFERROR($C$49,$C$32) | H98: =IFERROR(IF(F98>=G98,"✅ ATINGIDA","⏳ EM CURSO"),"---") | I98: =IFERROR(TEXT(MIN(100%,F98/MAX(1,G98)),"0%"),"-")
B99: Não | C99: =IFERROR(TEXT(EDATE(TODAY(),31),"MMM/YYYY"),"---") | D99: =IFERROR($C$58,0) | E99: =IFERROR(IF(MONTH(EDATE(TODAY(),31))=12,$C$12*0.5,0),0) | F99: =IFERROR(F98+IF(B99="Sim",D99+E99,0),0) | G99: =IFERROR($C$49,$C$32) | H99: =IFERROR(IF(F99>=G99,"✅ ATINGIDA","⏳ EM CURSO"),"---") | I99: =IFERROR(TEXT(MIN(100%,F99/MAX(1,G99)),"0%"),"-")
B100: Não | C100: =IFERROR(TEXT(EDATE(TODAY(),32),"MMM/YYYY"),"---") | D100: =IFERROR($C$58,0) | E100: =IFERROR(IF(MONTH(EDATE(TODAY(),32))=12,$C$12*0.5,0),0) | F100: =IFERROR(F99+IF(B100="Sim",D100+E100,0),0) | G100: =IFERROR($C$49,$C$32) | H100: =IFERROR(IF(F100>=G100,"✅ ATINGIDA","⏳ EM CURSO"),"---") | I100: =IFERROR(TEXT(MIN(100%,F100/MAX(1,G100)),"0%"),"-")
B101: Não | C101: =IFERROR(TEXT(EDATE(TODAY(),33),"MMM/YYYY"),"---") | D101: =IFERROR($C$58,0) | E101: =IFERROR(IF(MONTH(EDATE(TODAY(),33))=12,$C$12*0.5,0),0) | F101: =IFERROR(F100+IF(B101="Sim",D101+E101,0),0) | G101: =IFERROR($C$49,$C$32) | H101: =IFERROR(IF(F101>=G101,"✅ ATINGIDA","⏳ EM CURSO"),"---") | I101: =IFERROR(TEXT(MIN(100%,F101/MAX(1,G101)),"0%"),"-")
B102: Não | C102: =IFERROR(TEXT(EDATE(TODAY(),34),"MMM/YYYY"),"---") | D102: =IFERROR($C$58,0) | E102: =IFERROR(IF(MONTH(EDATE(TODAY(),34))=12,$C$12*0.5,0),0) | F102: =IFERROR(F101+IF(B102="Sim",D102+E102,0),0) | G102: =IFERROR($C$49,$C$32) | H102: =IFERROR(IF(F102>=G102,"✅ ATINGIDA","⏳ EM CURSO"),"---") | I102: =IFERROR(TEXT(MIN(100%,F102/MAX(1,G102)),"0%"),"-")
B103: Não | C103: =IFERROR(TEXT(EDATE(TODAY(),35),"MMM/YYYY"),"---") | D103: =IFERROR($C$58,0) | E103: =IFERROR(IF(MONTH(EDATE(TODAY(),35))=12,$C$12*0.5,0),0) | F103: =IFERROR(F102+IF(B103="Sim",D103+E103,0),0) | G103: =IFERROR($C$49,$C$32) | H103: =IFERROR(IF(F103>=G103,"✅ ATINGIDA","⏳ EM CURSO"),"---") | I103: =IFERROR(TEXT(MIN(100%,F103/MAX(1,G103)),"0%"),"-")
A105: 📂 CHECKLIST DE DOCUMENTAÇÃO
B106: 7. DOCUMENTOS NECESSÁRIOS PARA APROVAÇÃO
B107: Documento / Tarefa | C107: Responsável | D107: ✅ Concluído? | E107: 📅 Prazo | F107: Observação
B108: 1. RG e CPF do Cliente | C108: Cliente | D108: Não
B109: 2. Certidão de Estado Civil | C109: Cliente | D109: Não
B110: 3. Comprovantes de Renda (3 meses) | C110: Cliente | D110: Não
B111: 4. Comprovante de Residência | C111: Cliente | D111: Não
B112: 5. Extrato FGTS Atualizado | C112: Cliente | D112: Não
B113: 6. Declaração IRPF + Recibo | C113: Cliente | D113: Não
...
